{"document_name":[["Final_project_document.pdf"],["http://www.undp.org/content/dam/undp/documents/projects/PAL/00046328/Final_project_document.pdf"]],"end":"2013-12-31","fiscal_year":["2013"],"inst_descr":"UNDP - PAPP","inst_id":"02388","inst_type_descr":"UNDP","inst_type_id":"UND","operating_unit":"Prog for Palestinian People","operating_unit_id":"PAL","outputs":[{"award_id":"00046328","budget":[35331.4],"crs":"99810","crs_descr":"Sectors Not Specified","donor_budget":[35331.4,0.0],"donor_country":["MULTI-LATERAL AGENCY","OTHERS"],"donor_country_id":["MULTI_AGY","OTH"],"donor_expend":[0.0,12718.34],"donor_id":["00012","11012"],"donor_name":["Voluntary Contributions","WELFARE ASSOCIATION"],"donor_short":["UNDP","WELFARE"],"donor_type":["MULTI-LATERAL AGENCY","PRIVATE SECTOR"],"donor_type_id":["MULTI_AGY","PRIV"],"expenditure":[12718.34],"fiscal_year":["2013"],"focus_area":"-","focus_area_descr":"-","gender_descr":"Significant Objective","gender_id":"GEN2","output_descr":"The project aims at establishing a strategic framework of intervention for the Transfer of Knowledge through Expatriate Nationals (TOKTEN) programme","output_id":"00055098","output_title":"PAL/ Voulnteers for Developmen"}],"project_descr":"The project aims at establishing a strategic framework of intervention for the Transfer of Knowledge through Expatriate Nationals (TOKTEN) programme","project_id":"00046328","project_title":"PAL/ Voulnteers for Development (TOKTEN)","region_id":"PAPP","region_name":"Prog for Palestinian People","start":"2007-01-01","subnational":[]}