{"document_name":[["79476 - CTRAN Consulting Pvt  Ltd.pdf","79476 - RFP -CTRAN Consulting Pvt. Ltd.pdf","CTRAN Consulting - Contract.pdf","RFP-UNDP-2012-034.docx","2012 AWP Support Climate Change -79473.pdf","2012 AWP Support Development - 79474.pdf","AWP 2012 - Water Resource Management - 79476.pdf","2012 AUSAD Donor Report.docx","2012 AUSAID Donor Report Annex 2.docx","2012 AUSAID Donor Report Annex I.doc","Amendment to AUSAID agreement for 79473 79474 n 79476.pdf","AUSAID Agreement  for 79473  79474 n 79476.pdf","Project ID - 79473 - AWP 2011.pdf","Project ID - 79474 - AWP 2011.pdf","Project ID - 79476 - AWP 2011.pdf","Project Document - 79474.pdf","Project Document - 79476.pdf","Project Document - 79473.pdf"],["http://www.undp.org/content/dam/undp/documents/projects/IND/79476 - CTRAN Consulting Pvt  Ltd.pdf","http://www.undp.org/content/dam/undp/documents/projects/IND/79476 - RFP -CTRAN Consulting Pvt. Ltd.pdf","http://www.undp.org/content/dam/undp/documents/projects/IND/CTRAN Consulting - Contract.pdf","http://www.undp.org/content/dam/undp/documents/projects/IND/RFP-UNDP-2012-034.docx","http://www.undp.org/content/dam/undp/documents/projects/IND/2012 AWP Support Climate Change -79473.pdf","http://www.undp.org/content/dam/undp/documents/projects/IND/2012 AWP Support Development - 79474.pdf","http://www.undp.org/content/dam/undp/documents/projects/IND/AWP 2012 - Water Resource Management - 79476.pdf","http://www.undp.org/content/dam/undp/documents/projects/IND/2012 AUSAD Donor Report.docx","http://www.undp.org/content/dam/undp/documents/projects/IND/2012 AUSAID Donor Report Annex 2.docx","http://www.undp.org/content/dam/undp/documents/projects/IND/2012 AUSAID Donor Report Annex I.doc","http://www.undp.org/content/dam/undp/documents/projects/IND/Amendment to AUSAID agreement for 79473 79474 n 79476.pdf","http://www.undp.org/content/dam/undp/documents/projects/IND/AUSAID Agreement  for 79473  79474 n 79476.pdf","http://www.undp.org/content/dam/undp/documents/projects/IND/00062140/Project ID - 79473 - AWP 2011.pdf","http://www.undp.org/content/dam/undp/documents/projects/IND/00062140/Project ID - 79474 - AWP 2011.pdf","http://www.undp.org/content/dam/undp/documents/projects/IND/00062140/Project ID - 79476 - AWP 2011.pdf","http://www.undp.org/content/dam/undp/documents/projects/IND/00062140/Project Document - 79474.pdf","http://www.undp.org/content/dam/undp/documents/projects/IND/00062140/Project Document - 79476.pdf","http://www.undp.org/content/dam/undp/documents/projects/IND/00062140/Project Document - 79473.pdf"]],"end":"2014-06-3","fiscal_year":["2013"],"inst_descr":"UNDP","inst_id":"99999","inst_type_descr":"UNDP","inst_type_id":"UND","operating_unit":"India","operating_unit_id":"IND","outputs":[{"award_id":"00062140","budget":[350877.0],"crs":"41010","crs_descr":"Environmental policy and administrative management","donor_budget":[350877.0],"donor_country":["Australia"],"donor_country_id":["AUS"],"donor_expend":[37931.1],"donor_id":["11234"],"donor_name":["Australian Agency for International Development (AusAID)"],"donor_short":["AusAID"],"donor_type":["NON_PROGRAMME COUNTRY"],"donor_type_id":["NON_PROGCTY"],"expenditure":[37931.1],"fiscal_year":["2013"],"focus_area":"4","focus_area_descr":"Environment & sustainable development","gender_descr":"Significant Objective","gender_id":"GEN2","output_descr":"Water Resource Management for Climate Change Adaptation and Disaster Risk Reduction","output_id":"00079476","output_title":"Water Resource Management"},{"award_id":"00062140","budget":[205654.0],"crs":"41010","crs_descr":"Environmental policy and administrative management","donor_budget":[205654.0],"donor_country":["Australia"],"donor_country_id":["AUS"],"donor_expend":[71748.82],"donor_id":["11234"],"donor_name":["Australian Agency for International Development (AusAID)"],"donor_short":["AusAID"],"donor_type":["NON_PROGRAMME COUNTRY"],"donor_type_id":["NON_PROGCTY"],"expenditure":[71748.82],"fiscal_year":["2013"],"focus_area":"4","focus_area_descr":"Environment & sustainable development","gender_descr":"Significant Objective","gender_id":"GEN2","output_descr":"Development of Center for Climate Change at National Institute for Administrative Research (NIAR)","output_id":"00079474","output_title":"Climate Change Centre"},{"award_id":"00062140","budget":[435252.03],"crs":"41010","crs_descr":"Environmental policy and administrative management","donor_budget":[35252.03,400000.0],"donor_country":["MULTI-LATERAL AGENCY","Australia"],"donor_country_id":["MULTI_AGY","AUS"],"donor_expend":[35251.86,104454.72],"donor_id":["00012","11234"],"donor_name":["Voluntary Contributions","Australian Agency for International Development (AusAID)"],"donor_short":["UNDP","AusAID"],"donor_type":["MULTI-LATERAL AGENCY","NON_PROGRAMME COUNTRY"],"donor_type_id":["MULTI_AGY","NON_PROGCTY"],"expenditure":[139706.58],"fiscal_year":["2013"],"focus_area":"4","focus_area_descr":"Environment & sustainable development","gender_descr":"Significant Objective","gender_id":"GEN2","output_descr":"Support Climate Change Planning and Implementation Process in the country.","output_id":"00079473","output_title":"Climate Change Planning"}],"project_descr":"AUSAID-UNDP Partnership on Climate Change","project_id":"00062140","project_title":"AUSAID-UNDP Partnership on Climate Change","region_id":"RBAP","region_name":"Reg Bureau for Asia & Pacific","start":"2011-07-01","subnational":[{"lat":"19.4753","lon":"85.4929","precision":"3","scope":"2","type":"2"},{"lat":"21.5","lon":"75.3","precision":"3","scope":"2","type":"2"},{"lat":"23.3","lon":"78.3","precision":"4","scope":"3","type":"2"},{"lat":"23.3","lon":"78.3","precision":"4","scope":"3","type":"2"},{"lat":"23.45","lon":"85.3","precision":"4","scope":"3","type":"2"},{"lat":"23.45","lon":"85.3","precision":"4","scope":"3","type":"2"}]}